LICENSE
MANIFEST.in
README.rst
setup.py
Flask_Mitten.egg-info/PKG-INFO
Flask_Mitten.egg-info/SOURCES.txt
Flask_Mitten.egg-info/dependency_links.txt
Flask_Mitten.egg-info/namespace_packages.txt
Flask_Mitten.egg-info/not-zip-safe
Flask_Mitten.egg-info/requires.txt
Flask_Mitten.egg-info/top_level.txt
example/__init__.py
example/app.py
example/templates/error.html
example/templates/home.html
example/templates/index.html
example/templates/layout.html
example/templates/login.html
flaskext/__init__.py
flaskext/mitten.py
tests/tests.py