Metadata-Version: 1.0
Name: Flask-Mitten
Version: 0.2.1
Summary: Adds security functions to Flask applications for preventing some of the basic threats.
Home-page: https://github.com/lanius/flask-mitten
Author: lanius
Author-email: lanius@nirvake.org
License: BSD
Platform: any
Classifier: Development Status :: 4 - Beta
Classifier: Environment :: Web Environment
Classifier: Intended Audience :: Developers
Classifier: License :: OSI Approved :: BSD License
Classifier: Operating System :: OS Independent
Classifier: Programming Language :: Python
Classifier: Topic :: Internet :: WWW/HTTP :: Dynamic Content
Classifier: Topic :: Software Development :: Libraries :: Python Modules
